binance_candles/__init__.py
binance_candles/binance_candles.py
binance_candles-1.0.1.dist-info/METADATA
binance_candles-1.0.1.dist-info/WHEEL
binance_candles-1.0.1.dist-info/top_level.txt
binance_candles-1.0.1.dist-info/RECORD
